openhtf_docx_report/__init__.py
openhtf_docx_report-0.0.4.dist-info/LICENSE
openhtf_docx_report-0.0.4.dist-info/METADATA
openhtf_docx_report-0.0.4.dist-info/WHEEL
openhtf_docx_report-0.0.4.dist-info/top_level.txt
openhtf_docx_report-0.0.4.dist-info/RECORD
