Metadata-Version: 2.1
Name: openhtf-docx-report
Version: 0.0.4
Summary: Simple Openhtf MS-Word document test report callback
Home-page: https://github.com/UndyingScroll
Author: Kevin Pulley
Author-email: kpulley@imaginecommunications.com
License: UNKNOWN
Platform: UNKNOWN
Classifier: Programming Language :: Python :: 3
Classifier: License :: OSI Approved :: MIT License
Classifier: Operating System :: OS Independent
Requires-Python: >=3.6
License-File: LICENSE
Requires-Dist: docx
Requires-Dist: docxtpl
Requires-Dist: matplot
Requires-Dist: python-docx
